pubgapiku/__init__.py
pubgapiku/api_connector.py
pubgapiku/data_wrapper.py
pubgapi_ku-0.151.dist-info/LICENSE
pubgapi_ku-0.151.dist-info/METADATA
pubgapi_ku-0.151.dist-info/WHEEL
pubgapi_ku-0.151.dist-info/top_level.txt
pubgapi_ku-0.151.dist-info/RECORD
